fakturowniaAPI/__init__.py
fakturowniaAPI/client.py
fakturowniaAPI/enums.py
fakturowniaAPI/errors.py
fakturownia_python_api-0.1.dist-info/LICENSE
fakturownia_python_api-0.1.dist-info/METADATA
fakturownia_python_api-0.1.dist-info/WHEEL
fakturownia_python_api-0.1.dist-info/top_level.txt
fakturownia_python_api-0.1.dist-info/RECORD
