Metadata-Version: 2.1
Name: fakturownia-python-api
Version: 0.1
Summary: python library for fakturownia
Author: Michał Ogórek
Author-email: michal.ogorek03@gmail.com
Classifier: Programming Language :: Python :: 3
Classifier: License :: OSI Approved :: MIT License
Classifier: Operating System :: OS Independent
Requires-Python: >=3.9
License-File: LICENSE
